dfp/__init__.py
dfp/client.py
dfp/flags.py
dfp/protocol.py
dfp/server.py
dfp_protocol-0.1.0.dist-info/licenses/LICENSE
dfp_protocol-0.1.0.dist-info/METADATA
dfp_protocol-0.1.0.dist-info/WHEEL
dfp_protocol-0.1.0.dist-info/entry_points.txt
dfp_protocol-0.1.0.dist-info/top_level.txt
dfp_protocol-0.1.0.dist-info/RECORD
